beancount_balexpr/__init__.py
beancount_balexpr/balexpr.py
beancount_balexpr/balexpr_test.py
beancount_balexpr-0.5.0.dist-info/WHEEL
beancount_balexpr-0.5.0.dist-info/entry_points.txt
beancount_balexpr-0.5.0.dist-info/METADATA
beancount_balexpr-0.5.0.dist-info/RECORD
