Metadata-Version: 2.3
Name: beancount-balexpr
Version: 0.5.0
Summary: Check balances against simple expressions in beancount
Author: Di Weng
Author-email: Di Weng <dweng.cs@outlook.com>
Requires-Dist: beancount>=2.3.0
Requires-Dist: pytest>=4.6.11
Requires-Dist: setuptools>=44.1.1
Requires-Dist: wheel>=0.37.1
Requires-Python: >=3.3
